{
	"--border-radius": "--uq",
	"--color-anvr": "--tr",
	"--color-badge-background": "--ql",
	"--color-badge-icon": "--ap",
	"--color-badge-text": "--zo",
	"--color-black": "--jr",
	"--color-black-32": "--yp",
	"--color-black-75": "--zp",
	"--color-black-transparent": "--wk",
	"--color-black-transparent-low": "--lj",
	"--color-chip-background": "--bm",
	"--color-chip-background-active": "--ij",
	"--color-chip-background-hover": "--mj",
	"--color-chip-icon": "--op",
	"--color-chip-icon-active": "--rl",
	"--color-chip-icon-hover": "--cm",
	"--color-chip-text": "--np",
	"--color-currentcolor": "--tn",
	"--color-error": "--kr",
	"--color-error-critical": "--lm",
	"--color-error-high": "--vo",
	"--color-error-important": "--zl",
	"--color-error-low": "--lp",
	"--color-error-moderate": "--km",
	"--color-facebook": "--dq",
	"--color-focus": "--lr",
	"--color-focus-critical": "--nm",
	"--color-focus-gray": "--xo",
	"--color-focus-high": "--wo",
	"--color-focus-important": "--am",
	"--color-focus-low": "--mp",
	"--color-focus-moderate": "--mm",
	"--color-frame-dominant-100": "--hk",
	"--color-frame-dominant-200": "--ik",
	"--color-frame-dominant-300": "--jk",
	"--color-frame-dominant-400": "--kk",
	"--color-frame-dominant-50": "--el",
	"--color-frame-dominant-500": "--lk",
	"--color-frame-dominant-600": "--mk",
	"--color-frame-dominant-700": "--nk",
	"--color-frame-dominant-800": "--ok",
	"--color-frame-dominant-900": "--pk",
	"--color-header-footer-background": "--dj",
	"--color-header-footer-background-critical": "--ti",
	"--color-header-footer-background-high": "--vi",
	"--color-header-footer-background-important": "--ri",
	"--color-header-footer-background-low": "--wi",
	"--color-header-footer-background-moderate": "--si",
	"--color-header-navigation-background": "--xi",
	"--color-heading": "--qq",
	"--color-highlight": "--ip",
	"--color-highlight-critical": "--fk",
	"--color-highlight-high": "--im",
	"--color-highlight-important": "--uj",
	"--color-highlight-low": "--fn",
	"--color-highlight-moderate": "--ek",
	"--color-info": "--rr",
	"--color-info-critical": "--hn",
	"--color-info-high": "--kp",
	"--color-info-important": "--jm",
	"--color-info-low": "--bq",
	"--color-info-moderate": "--gn",
	"--color-instagram": "--qp",
	"--color-linkedin": "--eq",
	"--color-modal-backdrop": "--qm",
	"--color-pill": "--sr",
	"--color-pinterest": "--pp",
	"--color-primary": "--lq",
	"--color-primary-critical": "--ll",
	"--color-primary-high": "--vn",
	"--color-primary-important": "--xk",
	"--color-primary-low": "--go",
	"--color-primary-moderate": "--kl",
	"--color-reviews": "--rq",
	"--color-secondary": "--hp",
	"--color-secondary-critical": "--ck",
	"--color-secondary-high": "--hm",
	"--color-secondary-important": "--tj",
	"--color-secondary-low": "--dn",
	"--color-secondary-moderate": "--bk",
	"--color-selected": "--cq",
	"--color-selected-critical": "--dl",
	"--color-selected-high": "--in",
	"--color-selected-important": "--gk",
	"--color-selected-low": "--ao",
	"--color-selected-moderate": "--cl",
	"--color-subheading": "--yo",
	"--color-success": "--oq",
	"--color-success-active": "--pm",
	"--color-success-critical": "--nl",
	"--color-success-high": "--yn",
	"--color-success-important": "--al",
	"--color-success-low": "--jo",
	"--color-success-moderate": "--ml",
	"--color-tertiary": "--aq",
	"--color-tertiary-critical": "--zk",
	"--color-tertiary-high": "--en",
	"--color-tertiary-important": "--dk",
	"--color-tertiary-low": "--wn",
	"--color-tertiary-moderate": "--yk",
	"--color-text": "--qr",
	"--color-text-primary": "--un",
	"--color-text-quaternary": "--yl",
	"--color-text-secondary": "--gm",
	"--color-text-tertiary": "--cn",
	"--color-twitter": "--sq",
	"--color-ui": "--ds",
	"--color-ui-critical": "--io",
	"--color-ui-ground": "--jp",
	"--color-ui-high": "--nq",
	"--color-ui-high-transparent": "--wj",
	"--color-ui-important": "--xn",
	"--color-ui-low": "--fr",
	"--color-ui-moderate": "--ho",
	"--color-ui-root": "--mq",
	"--color-ui-root-half-transparent": "--cj",
	"--color-ui-root-transparent": "--vj",
	"--color-vimeo": "--mr",
	"--color-warning": "--pq",
	"--color-warning-critical": "--pl",
	"--color-warning-high": "--zn",
	"--color-warning-important": "--bl",
	"--color-warning-low": "--ko",
	"--color-warning-moderate": "--ol",
	"--color-white": "--ir",
	"--color-white-15": "--xp",
	"--color-white-35": "--wp",
	"--color-white-65": "--vp",
	"--color-white-transparent": "--vk",
	"--color-widget-background": "--gl",
	"--color-widget-heading": "--om",
	"--color-widget-subheading": "--fl",
	"--color-widget-submit-background": "--ej",
	"--color-widget-text": "--lo",
	"--color-youtube": "--tq",
	"--font-family-heading": "--jn",
	"--font-family-text": "--bp",
	"--litepicker-container-months-color-bg": "--ui",
	"--litepicker-day-color": "--sm",
	"--litepicker-day-color-hover": "--oj",
	"--litepicker-day-width": "--rm",
	"--litepicker-is-end-color": "--hl",
	"--litepicker-is-end-color-bg": "--qj",
	"--litepicker-is-end-color-bg-half": "--bj",
	"--litepicker-is-end-color-bg-image": "--aj",
	"--litepicker-is-in-range-color": "--jj",
	"--litepicker-is-locked-color": "--pj",
	"--litepicker-is-start-color": "--yj",
	"--litepicker-is-start-color-bg": "--kj",
	"--litepicker-is-start-color-bg-half": "--zi",
	"--litepicker-is-start-color-bg-image": "--yi",
	"--litepicker-is-today-color": "--xj",
	"--litepicker-month-header-color": "--gj",
	"--litepicker-month-weekday-color": "--fj",
	"--litepicker-month-width": "--sl",
	"--tw-backdrop-blur": "--cp",
	"--tw-backdrop-brightness": "--tl",
	"--tw-backdrop-contrast": "--vm",
	"--tw-backdrop-grayscale": "--em",
	"--tw-backdrop-hue-rotate": "--ul",
	"--tw-backdrop-invert": "--co",
	"--tw-backdrop-opacity": "--nn",
	"--tw-backdrop-saturate": "--wm",
	"--tw-backdrop-sepia": "--oo",
	"--tw-bg-opacity": "--vq",
	"--tw-blur": "--hs",
	"--tw-border-spacing-x": "--kn",
	"--tw-border-spacing-y": "--ln",
	"--tw-brightness": "--zq",
	"--tw-contain-layout": "--po",
	"--tw-contain-paint": "--dp",
	"--tw-contain-size": "--sp",
	"--tw-contain-style": "--ep",
	"--tw-content": "--xr",
	"--tw-contrast": "--nr",
	"--tw-divide-x-reverse": "--rn",
	"--tw-divide-y-reverse": "--sn",
	"--tw-drop-shadow": "--iq",
	"--tw-gradient-from": "--gp",
	"--tw-gradient-from-position": "--ak",
	"--tw-gradient-stops": "--uo",
	"--tw-gradient-to": "--kq",
	"--tw-gradient-to-position": "--il",
	"--tw-gradient-via-position": "--qk",
	"--tw-grayscale": "--gr",
	"--tw-hue-rotate": "--ar",
	"--tw-invert": "--cs",
	"--tw-numeric-figure": "--no",
	"--tw-numeric-fraction": "--mn",
	"--tw-numeric-spacing": "--bo",
	"--tw-ordinal": "--wr",
	"--tw-pan-x": "--es",
	"--tw-pan-y": "--fs",
	"--tw-pinch-zoom": "--wq",
	"--tw-prose-body": "--br",
	"--tw-prose-bold": "--dr",
	"--tw-prose-bullets": "--fp",
	"--tw-prose-captions": "--so",
	"--tw-prose-code": "--er",
	"--tw-prose-counters": "--ro",
	"--tw-prose-headings": "--qo",
	"--tw-prose-hr": "--pr",
	"--tw-prose-invert-body": "--ym",
	"--tw-prose-invert-bold": "--an",
	"--tw-prose-invert-bullets": "--jl",
	"--tw-prose-invert-captions": "--tk",
	"--tw-prose-invert-code": "--bn",
	"--tw-prose-invert-counters": "--sk",
	"--tw-prose-invert-headings": "--rk",
	"--tw-prose-invert-hr": "--do",
	"--tw-prose-invert-kbd": "--qn",
	"--tw-prose-invert-kbd-shadows": "--nj",
	"--tw-prose-invert-lead": "--zm",
	"--tw-prose-invert-links": "--fm",
	"--tw-prose-invert-pre-bg": "--xl",
	"--tw-prose-invert-pre-code": "--uk",
	"--tw-prose-invert-quote-borders": "--hj",
	"--tw-prose-invert-quotes": "--wl",
	"--tw-prose-invert-td-borders": "--sj",
	"--tw-prose-invert-th-borders": "--rj",
	"--tw-prose-kbd": "--hr",
	"--tw-prose-kbd-shadows": "--xm",
	"--tw-prose-lead": "--cr",
	"--tw-prose-links": "--jq",
	"--tw-prose-pre-bg": "--up",
	"--tw-prose-pre-code": "--to",
	"--tw-prose-quote-borders": "--vl",
	"--tw-prose-quotes": "--tp",
	"--tw-prose-td-borders": "--pn",
	"--tw-prose-th-borders": "--on",
	"--tw-ring-color": "--yq",
	"--tw-ring-inset": "--xq",
	"--tw-ring-offset-color": "--um",
	"--tw-ring-offset-shadow": "--dm",
	"--tw-ring-offset-width": "--tm",
	"--tw-ring-shadow": "--hq",
	"--tw-rotate": "--zr",
	"--tw-saturate": "--or",
	"--tw-scale-x": "--ur",
	"--tw-scale-y": "--vr",
	"--tw-scroll-snap-strictness": "--zj",
	"--tw-sepia": "--gs",
	"--tw-shadow": "--yr",
	"--tw-shadow-colored": "--mo",
	"--tw-skew-x": "--as",
	"--tw-skew-y": "--bs",
	"--tw-slashed-zero": "--rp",
	"--tw-space-x-reverse": "--eo",
	"--tw-space-y-reverse": "--fo",
	"--tw-translate-x": "--fq",
	"--tw-translate-y": "--gq",
	"-left-3": "qmd",
	"-left-7": "rmd",
	"-mb-3": "usd",
	"-ml-1": "vsd",
	"-ml-2": "wsd",
	"-ml-3": "xsd",
	"-ml-4": "ysd",
	"-ml-5": "zsd",
	"-ml-8": "atd",
	"-mt-0": "btd",
	"-mt-0\\.5": "egd",
	"-mt-1": "ctd",
	"-mt-18": "uqd",
	"-mt-2": "dtd",
	"-mt-28": "vqd",
	"-mt-36": "wqd",
	"-mt-5": "etd",
	"-mt-6": "ftd",
	"-mx-screen-w-half": "llc",
	"-right-1": "wfd",
	"-right-5": "xfd",
	"-rotate-90": "u8c",
	"-scale-100": "w8c",
	"-top-1": "hqd",
	"-top-28": "smd",
	"-top-36": "tmd",
	"-top-7": "iqd",
	"-top-px": "umd",
	"-translate-x-1": "utc",
	"-translate-x-1\\/2": "nlc",
	"-translate-y-1": "vtc",
	"-translate-y-1\\/2": "olc",
	"-z-50": "ssd",
	"\\!bg-secondary": "puc",
	"\\!border-0": "e9c",
	"\\!border-error-moderate": "fdc",
	"\\!gap-3": "eod",
	"\\!h-\\[100dvh\\]": "ptc",
	"\\!h-auto": "ggd",
	"\\!h-full": "hgd",
	"\\!justify-start": "erc",
	"\\!left-1": "vfd",
	"\\!left-1\\/2": "w3c",
	"\\!left-auto": "x3c",
	"\\!max-h-11": "y7c",
	"\\!max-h-\\[100dvh\\]": "qjc",
	"\\!max-h-none": "f0c",
	"\\!max-w-full": "i0c",
	"\\!min-h-\\[104px\\]": "mlc",
	"\\!min-w-map-info-card": "wec",
	"\\!p-0": "bud",
	"\\!p-1": "cud",
	"\\!p-1\\.5": "lid",
	"\\!p-3": "dud",
	"\\!pl-0": "isd",
	"\\!pl-3": "jsd",
	"\\!pl-4": "ksd",
	"\\!pr-14": "bpd",
	"\\!px-0": "hsd",
	"\\!rounded-full": "fuc",
	"\\!rounded-t-none": "ync",
	"\\!size-8": "fgd",
	"\\!text-lg": "wcd",
	"\\!top-0": "pmd",
	"\\!w-full": "ugd",
	"\\32xs\\:px-3": "e6c",
	"\\[\\&\\:\\:-moz-meter-bar\\]\\:bg-error-critical": "w6b",
	"\\[\\&\\:\\:-moz-meter-bar\\]\\:bg-error-high": "k7b",
	"\\[\\&\\:\\:-moz-meter-bar\\]\\:bg-highlight-high": "x6b",
	"\\[\\&\\:\\:-moz-meter-bar\\]\\:bg-success-high": "b7b",
	"\\[\\&\\:\\:-moz-meter-bar\\]\\:bg-transparent": "f7b",
	"\\[\\&\\:\\:-moz-meter-bar\\]\\:bg-warning-high": "c7b",
	"\\[\\&\\>\\*\\:nth-child\\(odd\\)\\>\\:not\\(\\:nth-child\\(1\\)\\)\\]\\:bg-ui-low": "z5b",
	"\\[\\&\\>\\*\\:nth-child\\(odd\\)\\>\\:not\\(\\:nth-child\\(1\\)\\)\\]\\:bg-ui-low>*": "y5b",
	"\\[\\&\\>\\*\\]\\:bg-icon-small": "icc",
	"\\[\\&\\>\\*\\]\\:bg-icon-small>*": "jac",
	"\\[\\&\\>\\*\\]\\:bg-no-repeat": "adc",
	"\\[\\&\\>\\*\\]\\:bg-no-repeat>*": "hbc",
	"\\[\\&\\>\\*\\]\\:bg-right-3-center": "g-b",
	"\\[\\&\\>\\*\\]\\:bg-right-3-center>*": "d9b",
	"\\[\\&\\>\\*\\]\\:bg-transparent": "jbc",
	"\\[\\&\\>\\*\\]\\:bg-transparent>*": "s-b",
	"\\[\\&\\>\\*\\]\\:cursor-pointer": "ibc",
	"\\[\\&\\>\\*\\]\\:cursor-pointer>*": "r-b",
	"\\[\\&\\>\\*\\]\\:gap-3": "jnc",
	"\\[\\&\\>\\*\\]\\:gap-3>*": "jjc",
	"\\[\\&\\>\\*\\]\\:h-full": "flc",
	"\\[\\&\\>\\*\\]\\:h-full>*": "khc",
	"\\[\\&\\>\\*\\]\\:items-center": "zcc",
	"\\[\\&\\>\\*\\]\\:items-center>*": "gbc",
	"\\[\\&\\>\\*\\]\\:max-w-full": "uec",
	"\\[\\&\\>\\*\\]\\:max-w-full>*": "ycc",
	"\\[\\&\\>\\*\\]\\:min-h-14": "mhc",
	"\\[\\&\\>\\*\\]\\:min-h-14>*": "sec",
	"\\[\\&\\>\\*\\]\\:pb-2": "mqc",
	"\\[\\&\\>\\*\\]\\:pb-2>*": "blc",
	"\\[\\&\\>\\*\\]\\:pt-2": "nqc",
	"\\[\\&\\>\\*\\]\\:pt-2>*": "clc",
	"\\[\\&\\>\\*\\]\\:px-4": "kqc",
	"\\[\\&\\>\\*\\]\\:px-4>*": "zkc",
	"\\[\\&\\>\\*\\]\\:py-2": "lqc",
	"\\[\\&\\>\\*\\]\\:py-2>*": "alc",
	"\\[\\&\\>\\*\\]\\:shrink-0": "nhc",
	"\\[\\&\\>\\*\\]\\:shrink-0>*": "tec",
	"\\[\\&\\>\\*\\]\\:text-left": "xfc",
	"\\[\\&\\>\\*\\]\\:text-left>*": "sdc",
	"\\[\\&\\>\\*\\]\\:w-full": "glc",
	"\\[\\&\\>\\*\\]\\:w-full>*": "lhc",
	"\\[\\&\\>\\:nth-child\\(2\\)\\]\\:p-0": "i-b",
	"\\[\\&\\>\\:nth-child\\(2\\)\\]\\:p-0>": "q9b",
	"\\[\\&\\>ng-component\\]\\:flex": "kbc",
	"\\[\\&\\>ng-component\\]\\:flex>ng-component": "l7b",
	"\\[\\&\\>ng-component\\]\\:grow": "lbc",
	"\\[\\&\\>ng-component\\]\\:grow>ng-component": "m7b",
	"\\[\\&\\[open\\]\\>summary\\:after\\]\\:rotate-180": "z6b",
	"\\[\\&_\\.gm-style-iw\\.gm-style-iw-c\\]\\:\\!min-w-map-info-card": "b6b",
	"\\[\\&_ui-sheet-header\\>\\*\\]\\:bg-ui-root": "s7b",
	"\\[\\@media\\(hover\\:hover\\)\\]\\:hover\\:bg-primary-high": "j6b",
	"\\[\\@media\\(hover\\:hover\\)\\]\\:hover\\:bg-primary-low": "n6b",
	"\\[\\@media\\(hover\\:hover\\)\\]\\:hover\\:bg-secondary-high": "g6b",
	"\\[\\@media\\(hover\\:hover\\)\\]\\:hover\\:bg-secondary-low": "i6b",
	"\\[\\@media\\(hover\\:hover\\)\\]\\:hover\\:bg-ui-high": "t6b",
	"\\[\\@media\\(hover\\:hover\\)\\]\\:hover\\:bg-ui-low": "v6b",
	"\\[\\@media\\(hover\\:hover\\)\\]\\:hover\\:border-primary-high": "d6b",
	"\\[\\@media\\(hover\\:hover\\)\\]\\:hover\\:border-secondary-high": "c6b",
	"\\[\\@media\\(hover\\:hover\\)\\]\\:hover\\:border-ui-important": "e6b",
	"\\[\\@media\\(hover\\:hover\\)\\]\\:hover\\:text-primary-high": "h6b",
	"\\[\\@media\\(hover\\:hover\\)\\]\\:hover\\:text-secondary-high": "f6b",
	"\\[overflow-wrap\\:anywhere\\]": "z-b",
	"active\\:bg-primary-critical": "dac",
	"active\\:bg-secondary-critical": "y9b",
	"active\\:bg-secondary-moderate": "z9b",
	"active\\:bg-transparent": "gec",
	"active\\:bg-ui-critical": "hec",
	"active\\:bg-ui-high": "nkc",
	"active\\:bg-ui-important": "qdc",
	"active\\:border-primary-critical": "w8b",
	"active\\:border-secondary-critical": "i8b",
	"active\\:border-ui-high": "fec",
	"active\\:border-ui-important": "cac",
	"active\\:outline-0": "smc",
	"active\\:shadow-input-focus": "zac",
	"active\\:text-primary-critical": "a-b",
	"active\\:text-secondary-critical": "x8b",
	"after\\:\\!bg-icon-chevron-down-light-text-secondary": "l6b",
	"after\\:\\[transform\\:scaleY\\(\\.65\\)_translateY\\(-75\\%\\)_rotate\\(45deg\\)\\]": "u5b",
	"after\\:aspect-square": "ugc",
	"after\\:bg-center": "bpc",
	"after\\:bg-hero-image-overlay-gradient": "u7b",
	"after\\:bg-hide-rotated-top": "vac",
	"after\\:bg-icon-chevron-down-regular-text-secondary": "m6b",
	"after\\:bg-no-repeat": "mic",
	"after\\:content-\\[\\'\\'\\]": "kdc",
	"after\\:h-full": "pyc",
	"after\\:inset-0": "ivc",
	"after\\:right-3": "jvc",
	"after\\:rounded-br": "qmc",
	"after\\:text-primary-moderate": "o-b",
	"after\\:top-0": "d2c",
	"after\\:top-full": "hsc",
	"after\\:transition-transform": "aac",
	"after\\:w-3": "j-c",
	"after\\:w-\\[calc\\(\\(sqrt\\(2\\)_\\*_100\\%\\)_\\/_2\\)\\]": "q6b",
	"after\\:w-full": "qyc",
	"align-middle": "n1c",
	"align-text-bottom": "kmc",
	"align-top": "vcd",
	"animate-drive-away": "tjc",
	"animate-horizontal-ratings": "oac",
	"animate-none": "l0c",
	"animate-rate-details-header-highlight": "t7b",
	"animate-skeleton-shine": "udc",
	"appearance-none": "crc",
	"aspect-16\\/9": "c0c",
	"aspect-square": "fxc",
	"aspect-video": "d0c",
	"autocomplete--multi": "kic",
	"autocomplete__clear-button": "sac",
	"autocomplete__clear-button--multi": "h8b",
	"autocomplete__entry-button": "tac",
	"backdrop-blur": "kyc",
	"backdrop-blur-\\[72px\\]": "bec",
	"backdrop-blur-xs": "apc",
	"backdrop-filter": "gsc",
	"basis-0": "znd",
	"basis-1": "aod",
	"basis-1\\/4": "n8c",
	"basis-2": "bod",
	"basis-2\\/3": "o8c",
	"basis-2\\/5": "p8c",
	"basis-3": "cod",
	"basis-32": "mhd",
	"basis-3\\/4": "q8c",
	"basis-3\\/5": "r8c",
	"basis-4": "dod",
	"basis-60": "nhd",
	"basis-80": "ohd",
	"basis-auto": "s8c",
	"basis-full": "t8c",
	"basis-horizontal-widget-autocomplete": "w7b",
	"basis-horizontal-widget-date-time": "g8b",
	"basis-horizontal-widget-dates": "u9b",
	"before\\:bg-icon-social-circle-solid-google-reviews-colored": "a6b",
	"before\\:bg-icon-social-official-trustpilot-white": "p6b",
	"before\\:bg-ui-low": "pmc",
	"before\\:h-5": "y5c",
	"before\\:inline-block": "tgc",
	"before\\:pb-aspect-ratio-1\\/1": "n-b",
	"before\\:w-5": "z5c",
	"bg-2": "uxd",
	"bg-2\\.5": "tod",
	"bg-3": "vxd",
	"bg-\\[\\#E6F2F1\\]": "vrc",
	"bg-\\[linear-gradient\\(180deg\\,rgba\\(0\\,109\\,104\\,0\\.15\\)_0\\%\\,rgba\\(255\\,255\\,255\\,0\\.15\\)_100\\%\\)\\]": "s5b",
	"bg-\\[rgba\\(0\\,0\\,0\\,0\\.04\\)\\]": "v9b",
	"bg-badge-background": "yhc",
	"bg-black": "hid",
	"bg-black-transparent": "hgc",
	"bg-black\\/40": "a1c",
	"bg-center": "rcd",
	"bg-chip-background": "zjc",
	"bg-contain": "t9c",
	"bg-cover": "jid",
	"bg-error-critical": "bmc",
	"bg-error-high": "dyc",
	"bg-error-low": "b1c",
	"bg-filter-map": "eyc",
	"bg-focus-low": "c1c",
	"bg-frame-dominant-200": "dfc",
	"bg-frame-dominant-50": "igc",
	"bg-gradient-to-t": "ooc",
	"bg-header-button-transparent": "k-b",
	"bg-header-footer": "joc",
	"bg-header-footer-critical": "rbc",
	"bg-header-navigation": "jgc",
	"bg-hero-gradient": "poc",
	"bg-hero-gradient-desktop": "ncc",
	"bg-hero-gradient-horizontal": "v-b",
	"bg-highlight": "d1c",
	"bg-highlight-high": "cmc",
	"bg-highlight-low": "koc",
	"bg-highlight-moderate": "efc",
	"bg-icon": "uod",
	"bg-icon-big": "m5c",
	"bg-icon-calendar-ui-critical": "l-b",
	"bg-icon-check-circle-solid-success": "b8b",
	"bg-icon-chevron-down-regular": "m-b",
	"bg-icon-chevron-right": "gfc",
	"bg-icon-chevron-right-bold-white": "m8b",
	"bg-icon-chevron-right-light": "w-b",
	"bg-icon-chevron-right-white": "x-b",
	"bg-icon-cross-ui-critical": "sbc",
	"bg-icon-exclamation-circle-solid-error": "o7b",
	"bg-icon-loader-ui-critical": "pac",
	"bg-icon-looking-glass-white": "y-b",
	"bg-icon-minus": "fyc",
	"bg-icon-plus": "i1c",
	"bg-icon-point-down-ui-critical": "g9b",
	"bg-icon-small": "gyc",
	"bg-icon-social-circle-solid-google-reviews-colored": "k6b",
	"bg-icon-social-official-trustpilot-colored": "y6b",
	"bg-icon-social-official-trustpilot-white": "d7b",
	"bg-image-underlay-gradient": "qac",
	"bg-info-low": "k5c",
	"bg-left-3-center": "roc",
	"bg-left-5-center": "soc",
	"bg-modal-backdrop": "dmc",
	"bg-no-repeat": "j1c",
	"bg-origin-content": "imc",
	"bg-page-gradient": "qoc",
	"bg-pill": "sod",
	"bg-primary": "p9c",
	"bg-primary-moderate": "zhc",
	"bg-right": "kid",
	"bg-right-3-center": "fmc",
	"bg-right-4-center": "gmc",
	"bg-right-9-center": "hmc",
	"bg-secondary": "e1c",
	"bg-secondary-high": "emc",
	"bg-secondary-low": "loc",
	"bg-selected": "l5c",
	"bg-selected-high": "moc",
	"bg-selected-important": "ffc",
	"bg-selected-low": "wrc",
	"bg-selected-moderate": "kgc",
	"bg-success-high": "xrc",
	"bg-success-low": "quc",
	"bg-success-moderate": "aic",
	"bg-transparent": "ruc",
	"bg-ui": "aud",
	"bg-ui-high": "q9c",
	"bg-ui-important": "yrc",
	"bg-ui-low": "pcd",
	"bg-ui-moderate": "suc",
	"bg-ui-root": "r9c",
	"bg-ui-root-half-transparent": "u-b",
	"bg-ui-root-transparent": "xdc",
	"bg-warning": "s9c",
	"bg-warning-high": "zrc",
	"bg-warning-low": "tuc",
	"bg-warning-moderate": "bic",
	"bg-white": "iid",
	"bg-white\\/15": "f1c",
	"bg-white\\/65": "g1c",
	"bg-white\\/80": "h1c",
	"bg-widget": "qcd",
	"bg-widget-submit": "noc",
	"border-0": "yhd",
	"border-1": "zhd",
	"border-2": "aid",
	"border-3": "bid",
	"border-b": "did",
	"border-b-0": "f9c",
	"border-b-1": "g9c",
	"border-b-2": "h9c",
	"border-b-4": "i9c",
	"border-b-ui-moderate": "dgc",
	"border-collapse": "brc",
	"border-dashed": "ayc",
	"border-double": "byc",
	"border-error": "x0c",
	"border-error-high": "amc",
	"border-error-important": "wdc",
	"border-focus": "y0c",
	"border-focus-critical": "bfc",
	"border-frame-dominant-300": "pbc",
	"border-frame-dominant-50": "kcc",
	"border-highlight-critical": "qbc",
	"border-l": "eid",
	"border-l-1": "j9c",
	"border-l-ui-moderate": "egc",
	"border-none": "j5c",
	"border-primary": "nuc",
	"border-r": "fid",
	"border-r-1": "k9c",
	"border-r-2": "l9c",
	"border-r-ui-moderate": "fgc",
	"border-secondary": "foc",
	"border-secondary-low": "cgc",
	"border-selected": "urc",
	"border-selected-low": "whc",
	"border-solid": "w0c",
	"border-success-active": "cfc",
	"border-success-important": "lcc",
	"border-t": "gid",
	"border-t-0": "m9c",
	"border-t-2": "n9c",
	"border-t-4": "o9c",
	"border-t-primary": "ioc",
	"border-t-ui-moderate": "ggc",
	"border-transparent": "wjc",
	"border-ui": "ocd",
	"border-ui-critical": "xjc",
	"border-ui-high": "ouc",
	"border-ui-important": "xhc",
	"border-ui-low": "cyc",
	"border-ui-moderate": "yjc",
	"border-warning-important": "mcc",
	"border-white": "z0c",
	"border-white\\/35": "goc",
	"border-white\\/65": "hoc",
	"border-y": "cid",
	"bottom-0": "yfd",
	"bottom-10": "bbd",
	"bottom-2": "zfd",
	"bottom-4": "agd",
	"bottom-6": "bgd",
	"bottom-auto": "y3c",
	"bottom-full": "z3c",
	"break-inside-avoid": "ujc",
	"break-normal": "r0c",
	"break-words": "i5c",
	"btn--arrow-shaped": "jlc",
	"btn-group": "ndd",
	"btn-group>*": "u5c",
	"btn-group>ui-popover": "ngc",
	"btn-primary": "v3c",
	"btn-secondary": "cxc",
	"btn-sm": "gqd",
	"btn-ui-moderate": "sqc",
	"button-next-month": "ilc",
	"button-previous-month": "vec",
	"checkbox--sm": "a2c",
	"checkbox-lg": "v5c",
	"checkbox__label--align-top": "uac",
	"checkbox__label--inline": "jdc",
	"checkbox__label--sm": "lic",
	"col-end-2": "fbd",
	"col-end-3": "gbd",
	"col-end-hero-background": "cdc",
	"col-end-hero-full": "klc",
	"col-span-1": "s7c",
	"col-span-2": "t7c",
	"col-span-3": "u7c",
	"col-span-4": "v7c",
	"col-span-full": "dxc",
	"col-start-1": "a4c",
	"col-start-2": "b4c",
	"col-start-3": "c4c",
	"columns-1": "ccd",
	"columns-2": "dcd",
	"columns-2xs": "r4c",
	"columns-3": "ecd",
	"columns-4": "fcd",
	"columns-5": "gcd",
	"content-end": "y4c",
	"cursor-default": "wtc",
	"cursor-pointer": "xtc",
	"cursor-text": "p4c",
	"cursor-tooltip": "ytc",
	"custom-details-arrow": "ogc",
	"custom-details-marker": "lfc",
	"custom-map": "m7c",
	"datepicker-inlined-scroll": "mbc",
	"datepicker-inlined-scroll>": "kac",
	"day-item": "sfd",
	"decoration-dotted": "nmc",
	"delay-one": "odd",
	"delay-three": "x5c",
	"delay-two": "pdd",
	"disabled\\:cursor-default": "rcc",
	"disabled\\:opacity-40": "vgc",
	"divide-none": "l7c",
	"divide-none>": "o0c",
	"divide-solid": "p3c",
	"divide-solid>": "sxc",
	"divide-ui-high": "uwc",
	"divide-ui-high>": "hrc",
	"divide-ui-low": "szc",
	"divide-ui-low>": "euc",
	"divide-ui-moderate": "dlc",
	"divide-ui-moderate>": "vhc",
	"divide-x-1": "sad",
	"divide-x-1>": "c5c",
	"divide-x-2": "tad",
	"divide-x-2>": "d5c",
	"divide-y": "mmd",
	"divide-y-0": "uad",
	"divide-y-0>": "e5c",
	"divide-y-1": "vad",
	"divide-y-1>": "f5c",
	"divide-y-2": "wad",
	"divide-y-2>": "g5c",
	"divide-y>": "kcd",
	"drop-shadow": "s5c",
	"drop-shadow-lg": "gvc",
	"duration-100": "x1c",
	"duration-1000": "lyc",
	"duration-200": "y1c",
	"duration-300": "z1c",
	"ease-in": "npd",
	"ease-in-out": "t5c",
	"ease-out": "sid",
	"er-dummy-search-box": "ohc",
	"er-search-form": "htc",
	"first\\:ml-0": "a6c",
	"first\\:mt-0": "b6c",
	"first\\:pl-0": "c6c",
	"flex-1": "yrd",
	"flex-auto": "wbd",
	"flex-col": "qhd",
	"flex-col-reverse": "wnc",
	"flex-grow": "xbd",
	"flex-grow-0": "o4c",
	"flex-nowrap": "x4c",
	"flex-row": "phd",
	"flex-row-reverse": "vnc",
	"flex-shrink": "n4c",
	"flex-shrink-0": "kxc",
	"flex-wrap": "hcd",
	"flex-wrap-reverse": "rlc",
	"float-right": "g4c",
	"focus-within\\:bg-icon-chevron-right-white": "a7b",
	"focus-within\\:bg-secondary-high": "v8b",
	"focus-within\\:outline": "mfc",
	"focus-within\\:outline-2": "mdc",
	"focus-within\\:outline-focus-critical": "x7b",
	"focus-within\\:outline-offset-2": "j9b",
	"focus-within\\:text-white": "pcc",
	"focus\\:border-2": "jsc",
	"focus\\:border-error-high": "qcc",
	"focus\\:border-focus": "pic",
	"focus\\:outline-1": "gpc",
	"focus\\:outline-2": "hpc",
	"focus\\:outline-error-moderate": "w9b",
	"focus\\:outline-focus-gray": "ybc",
	"focus\\:outline-focus-moderate": "x9b",
	"focus\\:outline-offset-2": "pdc",
	"focus\\:outline-transparent": "yac",
	"focus\\:outline-ui-high": "eec",
	"focus\\:shadow-input-error": "wbc",
	"focus\\:shadow-input-focus": "xbc",
	"focus\\:shadow-none": "mkc",
	"focus\\:shadow-stepperButton": "bac",
	"focus\\:shadow-stepperInput": "xac",
	"font-bold": "zcd",
	"font-default": "o1c",
	"font-extrabold": "avc",
	"font-heading": "p1c",
	"font-medium": "o5c",
	"font-normal": "p5c",
	"font-semibold": "hyc",
	"font-serif": "x9c",
	"from-frame-dominant-600": "gdc",
	"gap-0": "rtd",
	"gap-0\\.5": "rhd",
	"gap-1": "std",
	"gap-10": "asd",
	"gap-12": "bsd",
	"gap-1\\.5": "shd",
	"gap-2": "ttd",
	"gap-2\\.5": "thd",
	"gap-3": "utd",
	"gap-3\\.5": "uhd",
	"gap-4": "vtd",
	"gap-5": "wtd",
	"gap-6": "xtd",
	"gap-7": "ytd",
	"gap-8": "ztd",
	"gap-badge": "jcd",
	"gap-chip": "vhd",
	"gap-chip-sm": "b5c",
	"gap-x-0": "fod",
	"gap-x-0\\.5": "x8c",
	"gap-x-2": "god",
	"gap-x-3": "hod",
	"gap-x-4": "iod",
	"gap-x-5": "jod",
	"gap-x-9": "kod",
	"gap-y-0": "lod",
	"gap-y-1": "mod",
	"gap-y-10": "whd",
	"gap-y-1\\.5": "y8c",
	"gap-y-2": "nod",
	"gap-y-3": "ood",
	"gap-y-4": "pod",
	"gap-y-6": "qod",
	"gap-y-8": "rod",
	"gm-style": "pfd",
	"gm-style-iw": "k7c",
	"gm-style-iw-c": "xwc",
	"gm-style-iw-chr": "oqc",
	"gm-style-iw-d": "ywc",
	"gm-style-iw>button": "ljc",
	"grid-cols-1": "s4c",
	"grid-cols-2": "t4c",
	"grid-cols-3": "u4c",
	"grid-cols-4": "v4c",
	"grid-cols-6": "w4c",
	"grid-cols-\\[minmax\\(min-content\\,1fr\\)_repeat\\(1\\,minmax\\(0\\,1fr\\)\\)\\]": "v5b",
	"grid-cols-\\[minmax\\(min-content\\,1fr\\)_repeat\\(2\\,minmax\\(0\\,1fr\\)\\)\\]": "w5b",
	"grid-cols-\\[minmax\\(min-content\\,1fr\\)_repeat\\(3\\,minmax\\(0\\,1fr\\)\\)\\]": "x5b",
	"grid-cols-collection": "agc",
	"grid-cols-collection-desktop": "j-b",
	"grid-cols-cover-desktop": "edc",
	"grid-cols-cover-tablet": "vdc",
	"grid-cols-date-time": "uhc",
	"grid-cols-hero": "ztc",
	"grid-cols-hero-sm": "plc",
	"grid-cols-hero-xs": "qlc",
	"grid-flow-col": "oxc",
	"grid-flow-row": "nxc",
	"grid-rows-cover": "drc",
	"grid-rows-hero": "auc",
	"group-active\\:bg-chip-background-active": "h7b",
	"group-active\\:text-chip-icon-active": "z7b",
	"group-focus\\:outline": "wgc",
	"group-focus\\:outline-2": "kec",
	"group-focus\\:outline-focus-gray": "z8b",
	"group-focus\\:outline-offset-2": "b-b",
	"group-hover\\:animate-drive-away": "y8b",
	"group-hover\\:bg-chip-background-hover": "v7b",
	"group-hover\\:bg-ui-moderate": "eac",
	"group-hover\\:bg-white\\/15": "zbc",
	"group-hover\\:text-chip-icon-hover": "j8b",
	"group-last\\:border-b-0": "iec",
	"group-open\\:rotate-180": "jec",
	"grow-0": "zrd",
	"grow-\\[9999\\]": "lxc",
	"h-0": "h0d",
	"h-0\\.5": "erd",
	"h-1": "i0d",
	"h-10": "rwd",
	"h-11": "swd",
	"h-12": "twd",
	"h-14": "uwd",
	"h-16": "vwd",
	"h-2": "j0d",
	"h-20": "wwd",
	"h-24": "xwd",
	"h-2\\.5": "frd",
	"h-3": "k0d",
	"h-32": "ywd",
	"h-3\\.5": "grd",
	"h-4": "l0d",
	"h-4\\.5": "hrd",
	"h-5": "m0d",
	"h-6": "n0d",
	"h-60": "zwd",
	"h-7": "o0d",
	"h-72": "axd",
	"h-8": "p0d",
	"h-80": "bxd",
	"h-9": "q0d",
	"h-96": "cxd",
	"h-\\[500px\\]": "i4c",
	"h-\\[57px\\]": "x7c",
	"h-auto": "ird",
	"h-fit": "otd",
	"h-fit-content": "gxc",
	"h-full": "jrd",
	"h-lh": "dxd",
	"h-maps-mobile-sheet": "thc",
	"h-ratings-spacer": "onc",
	"h-screen": "igd",
	"h-sheet-like": "e0c",
	"hero-layout-desktop\\:-ml-3": "dbc",
	"hero-layout-desktop\\:-ml-8": "ebc",
	"hero-layout-desktop\\:bg-hero-gradient-desktop": "u6b",
	"hero-layout-desktop\\:col-end-hero-1\\/3": "q7b",
	"hero-layout-desktop\\:col-end-hero-2\\/3": "r7b",
	"hero-layout-desktop\\:col-start-2": "s8b",
	"hero-layout-desktop\\:col-start-hero-2\\/3": "e7b",
	"hero-layout-desktop\\:gap-4": "fbc",
	"hero-layout-desktop\\:mb-8": "dcc",
	"hero-layout-desktop\\:min-h-hero": "b9b",
	"hero-layout-desktop\\:mt-8": "ecc",
	"hero-layout-desktop\\:p-4": "wcc",
	"hero-layout-desktop\\:p-8": "xcc",
	"hero-layout-desktop\\:pb-6": "fcc",
	"hero-layout-desktop\\:pl-8": "gcc",
	"hero-layout-desktop\\:rounded-l-none": "a8b",
	"hero-layout-desktop\\:row-end-2": "n9b",
	"hero-layout-desktop\\:row-end-\\[span_2\\]": "i7b",
	"hero-layout-desktop\\:row-start-2": "t8b",
	"hero-layout-desktop\\:size-8": "hac",
	"hover\\:\\[\\&\\>\\*\\]\\:bg-focus-low": "f9b",
	"hover\\:\\[\\&\\>\\*\\]\\:bg-focus-low>*": "l8b",
	"hover\\:bg-header-footer-critical": "n8b",
	"hover\\:bg-secondary-low": "ndc",
	"hover\\:bg-selected": "kkc",
	"hover\\:bg-selected-high": "odc",
	"hover\\:bg-selected-low": "dec",
	"hover\\:bg-transparent": "nfc",
	"hover\\:bg-ui-high": "rmc",
	"hover\\:bg-ui-low": "fpc",
	"hover\\:bg-ui-moderate": "ofc",
	"hover\\:bg-white": "isc",
	"hover\\:bg-white\\/80": "oic",
	"hover\\:border-ui-moderate": "vbc",
	"hover\\:opacity-100": "lkc",
	"hover\\:scale-105": "epc",
	"hover\\:text-secondary": "pfc",
	"hover\\:text-secondary-high": "wac",
	"hyphens-auto": "q0c",
	"inline-block": "b0c",
	"inline-flex": "h4c",
	"input--invalid": "jtc",
	"input--valid": "vzc",
	"inset-0": "omd",
	"inset-auto": "q7c",
	"inset-x-auto": "wzc",
	"inset-y-auto": "xzc",
	"is-disabled": "w5c",
	"is-end-date": "s3c",
	"is-flipped": "n7c",
	"is-in-range": "t3c",
	"is-locked": "zad",
	"is-open": "opd",
	"is-open>": "lmd",
	"is-start-date": "bxc",
	"is-today": "tfd",
	"items-baseline": "buc",
	"items-center": "n0c",
	"items-end": "icd",
	"items-start": "z4c",
	"items-stretch": "pxc",
	"justify-between": "frc",
	"justify-center": "cuc",
	"justify-end": "a5c",
	"justify-evenly": "duc",
	"justify-start": "qxc",
	"justify-stretch": "grc",
	"last\\:border-b": "kvc",
	"last\\:border-b-0": "cpc",
	"last\\:border-r-0": "dpc",
	"last\\:mb-0": "k-c",
	"last\\:mr-0": "l-c",
	"last\\:rounded-tr-medium": "ldc",
	"leading-3": "add",
	"leading-4": "bdd",
	"leading-5": "cdd",
	"leading-6": "ddd",
	"leading-7": "edd",
	"leading-none": "r1c",
	"leading-tight": "iyc",
	"left-0": "jqd",
	"left-1": "kqd",
	"left-1\\/2": "cbd",
	"left-1\\/4": "dbd",
	"left-3": "lqd",
	"left-3\\.5": "ebd",
	"left-4": "mqd",
	"left-6": "nqd",
	"left-8": "oqd",
	"lg\\:-mt-18": "iad",
	"lg\\:-mt-2": "wed",
	"lg\\:-top-px": "c7c",
	"lg\\:animate-none": "iqc",
	"lg\\:basis-full": "qwc",
	"lg\\:before\\:-left-10": "jhc",
	"lg\\:before\\:-right-10": "vfc",
	"lg\\:before\\:bottom-20": "wfc",
	"lg\\:before\\:top-20": "ykc",
	"lg\\:bg-secondary": "jqc",
	"lg\\:bg-transparent": "wkc",
	"lg\\:bg-ui-moderate": "xkc",
	"lg\\:bg-ui-root": "swc",
	"lg\\:border-r-2": "rwc",
	"lg\\:bottom-10": "kzc",
	"lg\\:bottom-6": "l3c",
	"lg\\:col-span-2": "mwc",
	"lg\\:columns-2": "mzc",
	"lg\\:flex-nowrap": "etc",
	"lg\\:flex-row": "m3c",
	"lg\\:flex-wrap": "nzc",
	"lg\\:gap-0": "zed",
	"lg\\:gap-10": "pad",
	"lg\\:gap-12": "qad",
	"lg\\:gap-6": "afd",
	"lg\\:gap-8": "bfd",
	"lg\\:gap-x-9": "i7c",
	"lg\\:gap-y-0": "j7c",
	"lg\\:gap-y-10": "n3c",
	"lg\\:grid-cols-2": "btc",
	"lg\\:grid-cols-3": "ctc",
	"lg\\:grid-cols-4": "dtc",
	"lg\\:grid-cols-cover-desktop": "iac",
	"lg\\:grid-rows-cover": "gjc",
	"lg\\:grow-0": "oad",
	"lg\\:h-12": "wld",
	"lg\\:h-full": "kad",
	"lg\\:h-ratings-spacer": "hhc",
	"lg\\:inline-block": "hqc",
	"lg\\:max-h-none": "nwc",
	"lg\\:max-w-4xl": "lzc",
	"lg\\:max-w-\\[40\\.75rem\\]": "rdc",
	"lg\\:max-w-booking-car-selection-content": "j7b",
	"lg\\:max-w-full": "owc",
	"lg\\:max-w-none": "pwc",
	"lg\\:mb-10": "xed",
	"lg\\:mb-5": "uld",
	"lg\\:min-h-car-selection-filter": "o9b",
	"lg\\:ml-4": "vld",
	"lg\\:mt-10": "yed",
	"lg\\:mx-auto": "f7c",
	"lg\\:order-1": "d7c",
	"lg\\:order-2": "e7c",
	"lg\\:p-10": "yld",
	"lg\\:p-12": "zld",
	"lg\\:p-4": "eqd",
	"lg\\:p-6": "fqd",
	"lg\\:pb-0": "dmd",
	"lg\\:pb-8": "emd",
	"lg\\:pl-10": "ffd",
	"lg\\:pl-9": "fmd",
	"lg\\:pt-0": "gmd",
	"lg\\:pt-12": "gfd",
	"lg\\:pt-2": "hmd",
	"lg\\:pt-4": "imd",
	"lg\\:pt-6": "jmd",
	"lg\\:pt-9": "kmd",
	"lg\\:px-10": "cfd",
	"lg\\:px-12": "dfd",
	"lg\\:px-6": "amd",
	"lg\\:px-8": "bmd",
	"lg\\:py-10": "efd",
	"lg\\:py-3": "cmd",
	"lg\\:rounded-b-large": "ijc",
	"lg\\:rounded-button": "vkc",
	"lg\\:rounded-popover": "hjc",
	"lg\\:rounded-r-button": "ihc",
	"lg\\:shadow-md": "qzc",
	"lg\\:shadow-none": "ftc",
	"lg\\:size-6": "jad",
	"lg\\:text-base": "pzc",
	"lg\\:text-left": "ozc",
	"lg\\:text-white": "twc",
	"lg\\:top-10": "had",
	"lg\\:top-6": "ved",
	"lg\\:translate-x-0": "inc",
	"lg\\:w-12": "xld",
	"lg\\:w-1\\/2": "lad",
	"lg\\:w-4\\/12": "g7c",
	"lg\\:w-8\\/12": "h7c",
	"lg\\:w-\\[calc\\(33\\%\\+2\\.5rem\\)\\]": "c9b",
	"lg\\:w-auto": "mad",
	"lg\\:w-filter-sheet": "ukc",
	"lg\\:w-full": "nad",
	"lg\\:w-receipt-sheet": "fjc",
	"lg\\:z-10": "tld",
	"line-clamp-1": "zzc",
	"line-clamp-6": "a0c",
	"line-through": "v1c",
	"list-disc": "acd",
	"list-none": "bcd",
	"list-outside": "m0c",
	"m-0": "e0d",
	"m-0\\.5": "sqd",
	"m-1": "f0d",
	"m-28": "cvd",
	"m-4": "g0d",
	"m-auto": "tqd",
	"main-menu-mobile__item--hidden": "i9b",
	"map-container": "myc",
	"max-h-20": "jgd",
	"max-h-72": "kgd",
	"max-h-80": "lgd",
	"max-h-85vh": "z7c",
	"max-h-full": "a8c",
	"max-h-none": "b8c",
	"max-h-screen": "g0c",
	"max-h-sheet-like": "pnc",
	"max-hero-layout-desktop\\:mb-3": "e-b",
	"max-hero-layout-desktop\\:mb-32": "m9b",
	"max-lg\\:\\!h-full": "jpc",
	"max-lg\\:\\!max-h-none": "ygc",
	"max-lg\\:\\!rounded-t-none": "tcc",
	"max-lg\\:duration-300": "zgc",
	"max-lg\\:hidden": "lvc",
	"max-lg\\:rounded-t-popover-2x": "p-b",
	"max-lg\\:transition-\\[height\\]": "d-b",
	"max-lg\\:transition-all": "mec",
	"max-lg\\:w-full": "mvc",
	"max-md\\:bottom-0": "kpc",
	"max-md\\:bottom-auto": "sic",
	"max-md\\:flex-col": "npc",
	"max-md\\:h-maps-mobile-sheet": "fac",
	"max-md\\:h-sheet-like": "ahc",
	"max-md\\:hidden": "ovc",
	"max-md\\:left-0": "nvc",
	"max-md\\:max-h-sheet-like": "ucc",
	"max-md\\:max-w-sm": "mpc",
	"max-md\\:overflow-y-hidden": "acc",
	"max-md\\:px-3": "g2c",
	"max-md\\:rounded-t-popover-2x": "q-b",
	"max-md\\:w-12": "f2c",
	"max-md\\:w-full": "pvc",
	"max-md\\:w-screen": "lpc",
	"max-sm\\:\\!h-auto": "ppc",
	"max-sm\\:\\!h-full": "qpc",
	"max-sm\\:\\!hidden": "opc",
	"max-sm\\:\\!max-h-none": "bhc",
	"max-sm\\:\\!p-0": "tyc",
	"max-sm\\:\\!p-3": "uyc",
	"max-sm\\:\\!relative": "okc",
	"max-sm\\:\\!rounded-t-none": "vcc",
	"max-sm\\:\\[\\&\\>\\*\\]\\:bg-icon-chevron-right-light": "s6b",
	"max-sm\\:\\[\\&\\>\\*\\]\\:bg-icon-chevron-right-light>*": "o6b",
	"max-sm\\:\\[\\&\\>\\*\\]\\:font-bold": "h-b",
	"max-sm\\:\\[\\&\\>\\*\\]\\:font-bold>*": "e9b",
	"max-sm\\:\\[\\&\\>\\*\\]\\:min-h-14": "t-b",
	"max-sm\\:\\[\\&\\>\\*\\]\\:min-h-14>*": "p9b",
	"max-sm\\:\\[\\.autocomplete\\.is-open\\>\\&\\]\\:\\!top-0": "r6b",
	"max-sm\\:bg-modal-backdrop": "bcc",
	"max-sm\\:bg-ui-low": "tmc",
	"max-sm\\:border-ui-moderate": "bbc",
	"max-sm\\:border-y": "tpc",
	"max-sm\\:duration-300": "chc",
	"max-sm\\:fixed": "ryc",
	"max-sm\\:flex-col": "spc",
	"max-sm\\:font-bold": "umc",
	"max-sm\\:h-full": "svc",
	"max-sm\\:hidden": "rvc",
	"max-sm\\:justify-center": "oec",
	"max-sm\\:left-0": "qvc",
	"max-sm\\:max-h-full": "pkc",
	"max-sm\\:min-h-14": "rpc",
	"max-sm\\:min-h-8": "lsc",
	"max-sm\\:min-h-\\[45px\\]": "nec",
	"max-sm\\:min-h-mobile-input": "abc",
	"max-sm\\:p-3": "d6c",
	"max-sm\\:pt-1": "i2c",
	"max-sm\\:px-3": "h2c",
	"max-sm\\:py-1": "q3c",
	"max-sm\\:py-1\\.5": "msc",
	"max-sm\\:py-badge-sm": "tic",
	"max-sm\\:text-center": "uic",
	"max-sm\\:text-text-primary": "ccc",
	"max-sm\\:top-0": "syc",
	"max-sm\\:transition-\\[height\\]": "f-b",
	"max-sm\\:transition-all": "pec",
	"max-sm\\:w-full": "tvc",
	"max-w-1": "wnd",
	"max-w-1\\/2": "i8c",
	"max-w-20": "chd",
	"max-w-2xl": "obd",
	"max-w-2xs": "pbd",
	"max-w-3xl": "qbd",
	"max-w-48": "dhd",
	"max-w-4xl": "rbd",
	"max-w-56": "ehd",
	"max-w-5xl": "sbd",
	"max-w-6xl": "tbd",
	"max-w-7": "xnd",
	"max-w-7\\.5xl": "j0c",
	"max-w-7xl": "ubd",
	"max-w-80": "fhd",
	"max-w-9": "ynd",
	"max-w-9\\/10": "l4c",
	"max-w-\\[110px\\]": "zqc",
	"max-w-\\[200px\\]": "arc",
	"max-w-\\[220px\\]": "gtc",
	"max-w-\\[66\\%\\]": "ttc",
	"max-w-booking-car-selection-content": "y7b",
	"max-w-booking-content": "xec",
	"max-w-card": "j8c",
	"max-w-compare-1-rate": "zfc",
	"max-w-compare-2-rates": "yec",
	"max-w-compare-3-rates": "zec",
	"max-w-filter-tag": "rnc",
	"max-w-fit": "vbd",
	"max-w-full": "k8c",
	"max-w-hero": "l8c",
	"max-w-input-time": "snc",
	"max-w-lg": "ghd",
	"max-w-md": "hhd",
	"max-w-my-sunny-dashboard": "jcc",
	"max-w-none": "m8c",
	"max-w-optimized-reading": "ddc",
	"max-w-optimized-reading-heading": "u8b",
	"max-w-prose": "m4c",
	"max-w-sm": "ihd",
	"max-w-widget": "k0c",
	"max-w-widget-usp": "tnc",
	"max-w-xl": "jhd",
	"max-w-xs": "khd",
	"max-xs\\:hidden": "uvc",
	"mb-0": "mvd",
	"mb-0\\.5": "gnd",
	"mb-1": "nvd",
	"mb-10": "gtd",
	"mb-2": "ovd",
	"mb-3": "pvd",
	"mb-32": "htd",
	"mb-4": "qvd",
	"mb-5": "rvd",
	"mb-6": "svd",
	"mb-8": "tvd",
	"mb-auto": "hnd",
	"md\\:\\!text-lg": "jzc",
	"md\\:bg-secondary": "gqc",
	"md\\:bg-transparent": "tkc",
	"md\\:bg-ui-low": "hzc",
	"md\\:col-end-3": "dzc",
	"md\\:col-span-1": "ewc",
	"md\\:col-span-2": "fwc",
	"md\\:col-span-3": "gwc",
	"md\\:col-start-3": "tsc",
	"md\\:columns-3": "fzc",
	"md\\:flex-1": "ead",
	"md\\:flex-col": "h3c",
	"md\\:flex-row": "g3c",
	"md\\:flex-row-reverse": "ghc",
	"md\\:gap-1": "ofd",
	"md\\:gap-10": "gad",
	"md\\:gap-1\\.5": "i3c",
	"md\\:gap-2": "oed",
	"md\\:gap-3": "ped",
	"md\\:gap-4": "qed",
	"md\\:gap-6": "red",
	"md\\:gap-8": "sed",
	"md\\:grid-cols-2": "wsc",
	"md\\:grid-cols-3": "xsc",
	"md\\:grid-cols-6": "ysc",
	"md\\:grid-cols-collection-desktop": "r8b",
	"md\\:grid-cols-cover-tablet": "cbc",
	"md\\:grid-flow-col": "fnc",
	"md\\:grid-rows-cover": "ajc",
	"md\\:grow-0": "fad",
	"md\\:h-10": "qkd",
	"md\\:h-12": "rkd",
	"md\\:h-32": "skd",
	"md\\:h-4": "xpd",
	"md\\:h-60": "tkd",
	"md\\:h-96": "ukd",
	"md\\:h-9\\/10": "w6c",
	"md\\:h-fit": "med",
	"md\\:h-full": "z-c",
	"md\\:inline-block": "bqc",
	"md\\:inset-0": "u6c",
	"md\\:inset-x-auto": "zpc",
	"md\\:inset-y-auto": "aqc",
	"md\\:items-center": "dqc",
	"md\\:items-end": "gzc",
	"md\\:justify-between": "bjc",
	"md\\:justify-center": "skc",
	"md\\:justify-end": "zsc",
	"md\\:justify-start": "gnc",
	"md\\:left-3": "x-c",
	"md\\:m-28": "jkd",
	"md\\:m-4": "wpd",
	"md\\:m-auto": "y-c",
	"md\\:max-h-72": "d3c",
	"md\\:max-h-85vh": "hwc",
	"md\\:max-h-none": "iwc",
	"md\\:max-h-screen": "cqc",
	"md\\:max-w-3xl": "ezc",
	"md\\:max-w-9\\/10": "usc",
	"md\\:max-w-\\[50\\%\\]": "elc",
	"md\\:max-w-hero": "jwc",
	"md\\:max-w-md": "f3c",
	"md\\:max-w-none": "kwc",
	"md\\:max-w-prose": "vsc",
	"md\\:mb-0": "lkd",
	"md\\:mb-10": "jed",
	"md\\:mb-4": "mkd",
	"md\\:min-w-32": "e3c",
	"md\\:ml-0": "nkd",
	"md\\:mr-0": "okd",
	"md\\:mr-4": "pkd",
	"md\\:mt-12": "ked",
	"md\\:mt-24": "led",
	"md\\:mx-10": "ied",
	"md\\:mx-6": "kkd",
	"md\\:mx-auto": "v6c",
	"md\\:overflow-auto": "hnc",
	"md\\:overflow-hidden": "cjc",
	"md\\:p-0": "zpd",
	"md\\:p-3": "aqd",
	"md\\:p-4": "bqd",
	"md\\:p-6": "cqd",
	"md\\:p-8": "dqd",
	"md\\:pb-0": "gld",
	"md\\:pb-3\\/4": "z6c",
	"md\\:pb-5": "hld",
	"md\\:pb-6": "ild",
	"md\\:pb-8": "jld",
	"md\\:pl-0": "kld",
	"md\\:pl-14": "ued",
	"md\\:pl-6": "lld",
	"md\\:pl-8": "mld",
	"md\\:pr-0": "nld",
	"md\\:pr-3": "old",
	"md\\:prose-lg": "c2c",
	"md\\:prose-lg>": "oyc",
	"md\\:prose-lg>ol>li>p": "sgc",
	"md\\:prose-lg>ul>li": "jkc",
	"md\\:prose-lg>ul>li>p": "rgc",
	"md\\:pt-0": "pld",
	"md\\:pt-4": "qld",
	"md\\:pt-6": "rld",
	"md\\:pt-8": "sld",
	"md\\:px-3": "zkd",
	"md\\:px-4": "ald",
	"md\\:px-6": "bld",
	"md\\:px-8": "cld",
	"md\\:py-0": "nmd",
	"md\\:py-0\\.5": "y6c",
	"md\\:py-10": "ted",
	"md\\:py-2": "dld",
	"md\\:py-3": "eld",
	"md\\:py-5": "fld",
	"md\\:rounded-br-card": "djc",
	"md\\:rounded-card": "eqc",
	"md\\:rounded-none": "fqc",
	"md\\:rounded-popover-2x": "qec",
	"md\\:rounded-r-popover": "ufc",
	"md\\:rounded-tr-card": "ejc",
	"md\\:row-span-full": "cnc",
	"md\\:shadow-none": "atc",
	"md\\:text-5xl": "j3c",
	"md\\:text-6xl": "k3c",
	"md\\:text-left": "izc",
	"md\\:text-lg": "a7c",
	"md\\:text-right": "lwc",
	"md\\:text-xl": "b7c",
	"md\\:top-0": "hed",
	"md\\:w-12": "vkd",
	"md\\:w-1\\/3": "aad",
	"md\\:w-2\\/3": "bad",
	"md\\:w-32": "wkd",
	"md\\:w-4": "ypd",
	"md\\:w-80": "xkd",
	"md\\:w-96": "ykd",
	"md\\:w-\\[calc\\(50\\%_-_0\\.375rem\\)\\]": "f8b",
	"md\\:w-auto": "cad",
	"md\\:w-fit": "ned",
	"md\\:w-full": "dad",
	"md\\:w-modal-large": "dnc",
	"md\\:w-modal-medium": "rkc",
	"md\\:w-modal-small": "enc",
	"md\\:w-sheet": "x6c",
	"md\\:z-10": "ikd",
	"min-h-0": "qnd",
	"min-h-10": "mgd",
	"min-h-11": "ngd",
	"min-h-14": "ogd",
	"min-h-20": "pgd",
	"min-h-28": "qgd",
	"min-h-36": "rgd",
	"min-h-44": "sgd",
	"min-h-6": "rnd",
	"min-h-8": "snd",
	"min-h-80": "tgd",
	"min-h-\\[164px\\]": "tqc",
	"min-h-\\[390px\\]": "uqc",
	"min-h-car-selection-filter": "nac",
	"min-h-full": "c8c",
	"min-h-hero": "d8c",
	"min-h-input": "j4c",
	"min-h-mobile-input": "rjc",
	"min-h-popover-header": "yfc",
	"min-w-0": "und",
	"min-w-11": "wgd",
	"min-w-20": "xgd",
	"min-w-28": "ygd",
	"min-w-32": "zgd",
	"min-w-6": "vnd",
	"min-w-60": "ahd",
	"min-w-80": "bhd",
	"min-w-\\[100px\\]": "xqc",
	"min-w-\\[320px\\]": "yqc",
	"min-w-\\[min\\(calc\\(100dvw_-_\\(var\\(--custom-rem\\,_16px\\)\\*9\\.5\\)\\)\\,822px\\)\\]": "t5b",
	"min-w-fit": "mbd",
	"min-w-full": "h8c",
	"min-w-max": "nbd",
	"min-w-popover": "jxc",
	"min-w-widget-usp": "qnc",
	"mix-blend-multiply": "ckc",
	"ml-0": "uvd",
	"ml-1": "vvd",
	"ml-12": "itd",
	"ml-1\\.5": "ind",
	"ml-2": "wvd",
	"ml-3": "xvd",
	"ml-4": "yvd",
	"ml-5": "zvd",
	"ml-5\\.5": "jnd",
	"ml-6": "awd",
	"ml-\\[-1\\.75rem\\]": "nnc",
	"ml-auto": "knd",
	"month-item": "o7c",
	"month-item-header": "hlc",
	"month-item-name": "qqc",
	"month-item-weekdays-row": "bdc",
	"month-item-year": "rqc",
	"mr-0": "bwd",
	"mr-1": "cwd",
	"mr-12": "jtd",
	"mr-1\\.5": "lnd",
	"mr-2": "dwd",
	"mr-3": "ewd",
	"mr-4": "fwd",
	"mr-5": "gwd",
	"mr-6": "hwd",
	"mr-auto": "mnd",
	"mt-0": "iwd",
	"mt-0\\.5": "nnd",
	"mt-1": "jwd",
	"mt-10": "ktd",
	"mt-12": "ltd",
	"mt-2": "kwd",
	"mt-24": "mtd",
	"mt-3": "lwd",
	"mt-4": "mwd",
	"mt-5": "nwd",
	"mt-6": "owd",
	"mt-7": "pwd",
	"mt-8": "qwd",
	"mt-auto": "ond",
	"mt-px": "ntd",
	"mx-1": "dvd",
	"mx-10": "tsd",
	"mx-1\\.5": "dnd",
	"mx-2": "evd",
	"mx-2\\.5": "end",
	"mx-4": "fvd",
	"mx-6": "gvd",
	"mx-auto": "fnd",
	"my-0": "hvd",
	"my-1": "ivd",
	"my-2": "jvd",
	"my-3": "kvd",
	"my-4": "lvd",
	"object-contain": "uuc",
	"object-cover": "k1c",
	"object-right": "l1c",
	"object-scale-down": "jmc",
	"object-top": "u9c",
	"opacity-0": "fdd",
	"opacity-100": "q5c",
	"opacity-30": "b-c",
	"opacity-40": "c-c",
	"opacity-50": "d-c",
	"opacity-60": "e-c",
	"opacity-65": "f-c",
	"opacity-70": "g-c",
	"opacity-75": "h-c",
	"opacity-80": "i-c",
	"opacity-disabled": "yoc",
	"open\\:bg-icon-point-up-ui-critical": "c8b",
	"open\\:bg-left-5-top": "nic",
	"order-1": "bnd",
	"order-2": "cnd",
	"outline-1": "kdd",
	"outline-2": "ldd",
	"outline-8": "mdd",
	"outline-error-high": "fkc",
	"outline-error-moderate": "zdc",
	"outline-focus-gray": "gkc",
	"outline-focus-moderate": "aec",
	"outline-frame-dominant-200": "rac",
	"outline-none": "w1c",
	"outline-offset-2": "zoc",
	"outline-transparent": "iic",
	"overflow-auto": "txc",
	"overflow-ellipsis": "vlc",
	"overflow-hidden": "irc",
	"overflow-scroll": "jrc",
	"overflow-visible": "xnc",
	"overflow-x-hidden": "slc",
	"overflow-y-auto": "krc",
	"overflow-y-hidden": "tlc",
	"overflow-y-scroll": "ulc",
	"p-0": "b1d",
	"p-0\\.5": "csd",
	"p-1": "c1d",
	"p-10": "wxd",
	"p-12": "xxd",
	"p-1\\.5": "dsd",
	"p-2": "d1d",
	"p-2\\.5": "esd",
	"p-3": "e1d",
	"p-3\\.5": "fsd",
	"p-4": "f1d",
	"p-5": "g1d",
	"p-6": "h1d",
	"p-7": "i1d",
	"p-8": "j1d",
	"p-badge": "vod",
	"p-chip": "gsd",
	"p-chip-sm": "scd",
	"p-px": "yxd",
	"pac-container": "zwc",
	"pac-icon": "rfd",
	"pac-icon-marker": "pqc",
	"pac-item": "qfd",
	"pac-item>span": "axc",
	"page__content--catalog": "cec",
	"pb-0": "qyd",
	"pb-0\\.5": "cpd",
	"pb-1": "ryd",
	"pb-2": "syd",
	"pb-2\\.5": "dpd",
	"pb-3": "tyd",
	"pb-3\\/4": "epd",
	"pb-4": "uyd",
	"pb-5": "vyd",
	"pb-6": "wyd",
	"pb-8": "xyd",
	"pb-\\[41\\.67\\%\\]": "asc",
	"pb-aspect-ratio-16\\/9": "ifc",
	"pb-px": "jud",
	"pe-3": "yyd",
	"peer-focus\\:border-error-high": "c-b",
	"peer-focus\\:border-focus": "scc",
	"peer-focus\\:border-focus-critical": "k8b",
	"peer-focus\\:outline": "qic",
	"peer-focus\\:outline-1": "qfc",
	"peer-focus\\:outline-error-moderate": "d8b",
	"peer-focus\\:outline-focus-moderate": "e8b",
	"peer-focus\\:shadow-input-error": "k9b",
	"peer-focus\\:shadow-input-focus": "l9b",
	"peer-focus\\:shadow-toggleSwitch": "a9b",
	"picker-entry--selected-checked": "h9b",
	"pl-0": "zyd",
	"pl-0\\.5": "fpd",
	"pl-1": "azd",
	"pl-10": "kud",
	"pl-11": "lud",
	"pl-12": "mud",
	"pl-14": "nud",
	"pl-16": "oud",
	"pl-2": "bzd",
	"pl-2\\.5": "gpd",
	"pl-3": "czd",
	"pl-4": "dzd",
	"pl-5": "ezd",
	"pl-6": "fzd",
	"pl-7": "gzd",
	"pl-8": "hzd",
	"pl-9": "izd",
	"placeholder-text": "xoc",
	"pointer-events-auto": "shc",
	"pointer-events-none": "rhc",
	"popover--mobile-view-up-to-lg": "r9b",
	"popover--top": "tzc",
	"pr-0": "jzd",
	"pr-0\\.5": "hpd",
	"pr-1": "kzd",
	"pr-10": "pud",
	"pr-11": "qud",
	"pr-12": "rud",
	"pr-14": "sud",
	"pr-16": "tud",
	"pr-2": "lzd",
	"pr-20": "uud",
	"pr-3": "mzd",
	"pr-4": "nzd",
	"pr-5": "ozd",
	"pr-6": "pzd",
	"pr-7": "qzd",
	"pr-8": "rzd",
	"pr-9": "szd",
	"print\\:break-inside-avoid": "hcc",
	"prose-base": "p7c",
	"prose-base>": "u3c",
	"prose-base>ol>li>p": "njc",
	"prose-base>ul>li": "knc",
	"prose-base>ul>li>p": "mjc",
	"prose-h1\\:text-black": "xgc",
	"prose-invert": "uzc",
	"prose-lead\\:text-black": "lec",
	"prose-lead\\:text-xl": "ric",
	"prose-lg": "ufd",
	"prose-lg>": "abd",
	"prose-lg>ol>li>p": "mnc",
	"prose-lg>ul>li": "itc",
	"prose-lg>ul>li>p": "lnc",
	"prose-p\\:inline": "ksc",
	"prose-p\\:m-0": "e2c",
	"prose-p\\:text-sm": "ipc",
	"prose-text-black-sm": "qhc",
	"ps-0": "tzd",
	"pt-0": "uzd",
	"pt-1": "vzd",
	"pt-10": "vud",
	"pt-12": "wud",
	"pt-2": "wzd",
	"pt-2\\.5": "ipd",
	"pt-3": "xzd",
	"pt-4": "yzd",
	"pt-6": "zzd",
	"pt-7": "a0d",
	"pt-8": "b0d",
	"pt-9": "c0d",
	"px-0": "zxd",
	"px-1": "ayd",
	"px-10": "eud",
	"px-12": "fud",
	"px-2": "byd",
	"px-2\\.5": "wod",
	"px-3": "cyd",
	"px-4": "dyd",
	"px-5": "eyd",
	"px-6": "fyd",
	"px-8": "gyd",
	"px-9": "hyd",
	"px-screen-w-half": "toc",
	"py-0": "iyd",
	"py-0\\.5": "xod",
	"py-1": "jyd",
	"py-10": "gud",
	"py-12": "hud",
	"py-1\\.5": "yod",
	"py-2": "kyd",
	"py-20": "iud",
	"py-2\\.5": "zod",
	"py-3": "lyd",
	"py-3\\.5": "apd",
	"py-4": "myd",
	"py-5": "nyd",
	"py-6": "oyd",
	"py-8": "pyd",
	"py-chip-y": "tcd",
	"py-chip-y-sm": "m1c",
	"right-0": "vmd",
	"right-1": "wmd",
	"right-2": "xmd",
	"right-3": "ymd",
	"right-3\\.5": "r7c",
	"right-4": "zmd",
	"right-8": "and",
	"rotate-180": "v8c",
	"rotate-90": "ybd",
	"rounded-b": "lcd",
	"rounded-b-button": "znc",
	"rounded-b-card": "iuc",
	"rounded-b-large": "mrc",
	"rounded-b-medium": "aoc",
	"rounded-badge": "wxc",
	"rounded-bl-none": "orc",
	"rounded-br-card": "prc",
	"rounded-br-none": "qrc",
	"rounded-button": "guc",
	"rounded-card": "s0c",
	"rounded-chip": "t0c",
	"rounded-full": "u0c",
	"rounded-horizontal-widget": "obc",
	"rounded-input": "xxc",
	"rounded-l-medium": "boc",
	"rounded-l-none": "juc",
	"rounded-large": "yxc",
	"rounded-medium": "huc",
	"rounded-none": "v0c",
	"rounded-popover": "lrc",
	"rounded-popover-2x": "vjc",
	"rounded-r": "mcd",
	"rounded-r-button": "coc",
	"rounded-r-full": "kuc",
	"rounded-r-medium": "doc",
	"rounded-r-none": "luc",
	"rounded-r-popover": "ylc",
	"rounded-rate-card-box": "afc",
	"rounded-small": "zxc",
	"rounded-t": "ncd",
	"rounded-t-button": "eoc",
	"rounded-t-large": "nrc",
	"rounded-t-none": "muc",
	"rounded-t-popover-2x": "bgc",
	"rounded-tl-medium": "zlc",
	"rounded-tl-none": "rrc",
	"rounded-tr-card": "src",
	"rounded-tr-none": "trc",
	"row-end-1": "hbd",
	"row-end-2": "ibd",
	"row-end-5": "jbd",
	"row-end-\\[span_1\\]": "ojc",
	"row-end-\\[span_4\\]": "pjc",
	"row-span-1": "w7c",
	"row-span-full": "exc",
	"row-start-1": "d4c",
	"row-start-2": "e4c",
	"row-start-4": "f4c",
	"scale-100": "zbd",
	"scroll-smooth": "uxc",
	"segmented-control--invalid": "lac",
	"segmented-control__button": "nbc",
	"segmented-control__button--is-vertical": "n7b",
	"segmented-control__divider": "mac",
	"segmented-control__divider--is-vertical": "g7b",
	"select-none": "q4c",
	"self-center": "h5c",
	"self-end": "xhd",
	"self-start": "d9c",
	"self-stretch": "p0c",
	"shadow-input-error": "dkc",
	"shadow-input-focus": "ekc",
	"shadow-lg": "gdd",
	"shadow-md": "hdd",
	"shadow-nav-menu-inner": "jfc",
	"shadow-none": "r5c",
	"shadow-sm": "idd",
	"shadow-toggleSwitch": "hic",
	"shadow-xl": "jdd",
	"shrink-0": "lhd",
	"size-2": "xqd",
	"size-20": "pnd",
	"size-2\\.5": "kbd",
	"size-3": "yqd",
	"size-4": "zqd",
	"size-5": "ard",
	"size-6": "brd",
	"size-7": "crd",
	"size-8": "drd",
	"size-avatar-lg": "ktc",
	"size-avatar-md": "ltc",
	"size-avatar-sm": "mtc",
	"size-avatar-xl": "ntc",
	"size-avatar-xs": "otc",
	"size-full": "lbd",
	"skip-ink-none": "wwc",
	"sm\\:-translate-y-1\\/2": "sfc",
	"sm\\:basis-1\\/3": "zvc",
	"sm\\:basis-2\\/3": "awc",
	"sm\\:basis-2\\/5": "bwc",
	"sm\\:basis-3\\/5": "cwc",
	"sm\\:basis-auto": "dwc",
	"sm\\:before\\:-left-8": "zic",
	"sm\\:before\\:-right-8": "ehc",
	"sm\\:before\\:bottom-8": "fhc",
	"sm\\:before\\:top-8": "bnc",
	"sm\\:bg-header-button-transparent": "q8b",
	"sm\\:bg-icon": "r6c",
	"sm\\:bg-ui-low": "zyc",
	"sm\\:border-0": "y2c",
	"sm\\:border-l": "z2c",
	"sm\\:bottom-4": "q2c",
	"sm\\:col-span-2": "wvc",
	"sm\\:columns-2": "xyc",
	"sm\\:flex-col": "w2c",
	"sm\\:flex-grow-0": "psc",
	"sm\\:flex-nowrap": "ssc",
	"sm\\:flex-row": "v2c",
	"sm\\:gap-0": "vdd",
	"sm\\:gap-1": "wdd",
	"sm\\:gap-2": "xdd",
	"sm\\:gap-3": "ydd",
	"sm\\:gap-4": "zdd",
	"sm\\:gap-5": "aed",
	"sm\\:gap-6": "bed",
	"sm\\:gap-7": "ced",
	"sm\\:gap-8": "ded",
	"sm\\:gap-x-5": "p6c",
	"sm\\:gap-y-10": "x2c",
	"sm\\:gap-y-8": "q6c",
	"sm\\:grid-cols-2": "qsc",
	"sm\\:grid-cols-3": "rsc",
	"sm\\:grid-cols-collection-desktop": "p8b",
	"sm\\:grid-cols-hero-sm": "tfc",
	"sm\\:grow-0": "w-c",
	"sm\\:h-9": "spd",
	"sm\\:h-full": "r-c",
	"sm\\:inline-block": "vpc",
	"sm\\:items-center": "xpc",
	"sm\\:items-end": "yyc",
	"sm\\:items-stretch": "ymc",
	"sm\\:justify-start": "zmc",
	"sm\\:leading-none": "ypc",
	"sm\\:leading-tight": "anc",
	"sm\\:left-4": "p-c",
	"sm\\:line-clamp-6": "upc",
	"sm\\:max-h-80": "s2c",
	"sm\\:max-h-full": "xvc",
	"sm\\:max-w-\\[136px\\]": "xic",
	"sm\\:max-w-card": "yvc",
	"sm\\:max-w-xs": "u2c",
	"sm\\:mb-5": "hjd",
	"sm\\:mb-8": "ijd",
	"sm\\:min-h-0": "o6c",
	"sm\\:min-h-\\[375px\\]": "wic",
	"sm\\:min-h-input": "osc",
	"sm\\:min-w-80": "t2c",
	"sm\\:min-w-popover": "xmc",
	"sm\\:mr-2": "jjd",
	"sm\\:mr-5": "kjd",
	"sm\\:mt-0": "ljd",
	"sm\\:mt-5": "mjd",
	"sm\\:mt-8": "njd",
	"sm\\:overflow-visible": "dhc",
	"sm\\:p-12": "vjd",
	"sm\\:p-4": "tpd",
	"sm\\:p-6": "upd",
	"sm\\:p-8": "vpd",
	"sm\\:pb-0": "ekd",
	"sm\\:pb-8": "fkd",
	"sm\\:pl-12": "ged",
	"sm\\:prose-lg": "b2c",
	"sm\\:prose-lg>": "nyc",
	"sm\\:prose-lg>ol>li>p": "qgc",
	"sm\\:prose-lg>ul>li": "ikc",
	"sm\\:prose-lg>ul>li>p": "pgc",
	"sm\\:pt-4": "gkd",
	"sm\\:pt-6": "hkd",
	"sm\\:px-0": "wjd",
	"sm\\:px-12": "eed",
	"sm\\:px-2": "xjd",
	"sm\\:px-3": "yjd",
	"sm\\:px-4": "zjd",
	"sm\\:px-8": "akd",
	"sm\\:px-9": "bkd",
	"sm\\:py-20": "fed",
	"sm\\:py-3": "ckd",
	"sm\\:py-8": "dkd",
	"sm\\:right-0": "n6c",
	"sm\\:rounded-popover": "yic",
	"sm\\:shadow-lg": "bzc",
	"sm\\:shadow-md": "czc",
	"sm\\:size-4": "q-c",
	"sm\\:size-5": "xad",
	"sm\\:size-5\\.5": "wyc",
	"sm\\:text-2xl": "a3c",
	"sm\\:text-3xl": "b3c",
	"sm\\:text-5xl": "c3c",
	"sm\\:text-base": "azc",
	"sm\\:text-sm": "s6c",
	"sm\\:text-xl": "t6c",
	"sm\\:top-1\\/2": "r2c",
	"sm\\:top-4": "sdd",
	"sm\\:w-10": "ojd",
	"sm\\:w-1\\/3": "s-c",
	"sm\\:w-20": "pjd",
	"sm\\:w-24": "qjd",
	"sm\\:w-2\\/3": "t-c",
	"sm\\:w-36": "rjd",
	"sm\\:w-40": "sjd",
	"sm\\:w-52": "tjd",
	"sm\\:w-80": "ujd",
	"sm\\:w-\\[61\\.8\\%\\]": "wmc",
	"sm\\:w-\\[calc\\(33\\.33\\%\\+2rem\\)\\]": "o8b",
	"sm\\:w-auto": "u-c",
	"sm\\:w-fit": "tdd",
	"sm\\:w-form-control": "qkc",
	"sm\\:w-form-label": "wpc",
	"sm\\:w-full": "v-c",
	"sm\\:w-max": "udd",
	"space-x-1": "ifd",
	"space-x-1>": "z8c",
	"space-y-2": "jfd",
	"space-y-2>": "a9c",
	"space-y-3": "kfd",
	"space-y-3>": "b9c",
	"space-y-3\\.5": "o3c",
	"space-y-3\\.5>": "rxc",
	"space-y-8": "lfd",
	"space-y-8>": "c9c",
	"text-0": "lsd",
	"text-2xl": "mid",
	"text-2xs": "nid",
	"text-3xl": "oid",
	"text-4xl": "pid",
	"text-5xl": "qid",
	"text-6xl": "rid",
	"text-anchor-middle": "kjc",
	"text-avatar-lg": "vuc",
	"text-avatar-md": "wuc",
	"text-avatar-sm": "xuc",
	"text-avatar-xl": "yuc",
	"text-avatar-xs": "zuc",
	"text-badge-icon": "csc",
	"text-badge-text": "dsc",
	"text-base": "xcd",
	"text-black": "y9c",
	"text-center": "n5c",
	"text-chip": "ycd",
	"text-chip-icon": "bvc",
	"text-chip-sm": "q1c",
	"text-chip-text": "cvc",
	"text-currentcolor": "lmc",
	"text-ellipsis": "vxc",
	"text-error": "z9c",
	"text-error-high": "esc",
	"text-frame-dominant-500": "hdc",
	"text-heading": "s1c",
	"text-highlight-high": "cic",
	"text-left": "ucd",
	"text-lg": "jpd",
	"text-primary": "t1c",
	"text-right": "v9c",
	"text-secondary": "dvc",
	"text-secondary-critical": "idc",
	"text-secondary-high": "dic",
	"text-secondary-important": "occ",
	"text-shadow-primary": "jic",
	"text-shadow-secondary": "kfc",
	"text-sm": "kpd",
	"text-start": "w9c",
	"text-subheading": "fsc",
	"text-success-active": "eic",
	"text-tertiary": "jyc",
	"text-text-primary": "mmc",
	"text-text-quaternary": "lgc",
	"text-text-secondary": "fic",
	"text-text-tertiary": "akc",
	"text-transparent": "voc",
	"text-ui-root": "u1c",
	"text-white": "a-c",
	"text-white\\/65": "evc",
	"text-white\\/80": "fvc",
	"text-widget-heading": "gic",
	"text-widget-subheading": "ydc",
	"text-widget-text": "woc",
	"text-xl": "lpd",
	"text-xs": "mpd",
	"tippy-arrow": "r3c",
	"tippy-box": "yad",
	"tippy-content": "vwc",
	"to-frame-dominant-300": "hfc",
	"top-0": "msd",
	"top-0\\.5": "cgd",
	"top-1": "nsd",
	"top-10": "pqd",
	"top-14": "qqd",
	"top-1\\/2": "dgd",
	"top-20": "rqd",
	"top-3": "osd",
	"top-4": "psd",
	"top-5": "qsd",
	"top-6": "rsd",
	"top-\\[57px\\]": "yzc",
	"top-\\[calc\\(114px_\\+_57px\\)\\]": "s9b",
	"top-\\[calc\\(154px_\\+_57px\\)\\]": "t9b",
	"tracking-custom-promotion": "tbc",
	"tracking-tighter": "uoc",
	"tracking-widest": "bsc",
	"transition-\\[max-height\\]": "ubc",
	"transition-\\[width\\,background-color\\]": "p7b",
	"transition-all": "hvc",
	"transition-colors": "omc",
	"transition-opacity": "hkc",
	"transition-transform": "mgc",
	"translate-x-0": "mxc",
	"translate-x-full": "unc",
	"uc-embedding-accept": "phc",
	"uc-embedding-more-info": "tdc",
	"underline-offset-4": "bkc",
	"w-0": "r0d",
	"w-1": "s0d",
	"w-10": "exd",
	"w-11": "fxd",
	"w-12": "gxd",
	"w-14": "hxd",
	"w-16": "ixd",
	"w-1\\/2": "krd",
	"w-1\\/3": "lrd",
	"w-1\\/4": "mrd",
	"w-1\\/5": "nrd",
	"w-2": "t0d",
	"w-20": "jxd",
	"w-24": "kxd",
	"w-2\\.5": "ord",
	"w-2\\/3": "prd",
	"w-2\\/5": "qrd",
	"w-3": "u0d",
	"w-32": "lxd",
	"w-36": "mxd",
	"w-3\\/4": "rrd",
	"w-3\\/5": "srd",
	"w-4": "v0d",
	"w-40": "nxd",
	"w-48": "oxd",
	"w-4\\.5": "trd",
	"w-4\\/5": "urd",
	"w-5": "w0d",
	"w-52": "pxd",
	"w-56": "qxd",
	"w-6": "x0d",
	"w-7": "y0d",
	"w-8": "z0d",
	"w-80": "rxd",
	"w-8\\.5": "vrd",
	"w-9": "a1d",
	"w-96": "sxd",
	"w-\\[23\\%\\]": "e8c",
	"w-\\[30\\%\\]": "f8c",
	"w-\\[47\\%\\]": "g8c",
	"w-\\[640px\\]": "k4c",
	"w-auto": "wrd",
	"w-filter-sheet": "qtc",
	"w-fit": "ptd",
	"w-form-control": "rtc",
	"w-form-label": "h0c",
	"w-full": "xrd",
	"w-map-info-card": "vqc",
	"w-max": "qtd",
	"w-modal-large": "hxc",
	"w-modal-medium": "stc",
	"w-modal-small": "ixc",
	"w-px": "txd",
	"w-receipt-sheet": "wqc",
	"w-receipt-sheet-xl": "sjc",
	"w-screen": "vgd",
	"w-sheet": "tnd",
	"whitespace-normal": "wlc",
	"whitespace-nowrap": "xlc",
	"xl\\:columns-3": "rzc",
	"xl\\:gap-12": "rad",
	"xl\\:gap-3": "hfd",
	"xl\\:w-receipt-sheet-xl": "rec",
	"xs\\:-mt-36": "m-c",
	"xs\\:-top-36": "f6c",
	"xs\\:col-end-hero-background": "gac",
	"xs\\:col-start-2": "nsc",
	"xs\\:flex-row": "k2c",
	"xs\\:gap-0": "mfd",
	"xs\\:gap-0\\.5": "l2c",
	"xs\\:gap-1": "nfd",
	"xs\\:gap-1\\.5": "m2c",
	"xs\\:gap-5": "qdd",
	"xs\\:gap-6": "rdd",
	"xs\\:gap-y-6": "h6c",
	"xs\\:gap-y-8": "i6c",
	"xs\\:grid-cols-hero-xs": "rfc",
	"xs\\:h-auto": "n-c",
	"xs\\:inset-auto": "vvc",
	"xs\\:max-w-\\[320px\\]": "vic",
	"xs\\:mb-0": "tid",
	"xs\\:mb-6": "uid",
	"xs\\:min-h-36": "j2c",
	"xs\\:mt-5": "vid",
	"xs\\:mt-6": "wid",
	"xs\\:p-1": "ppd",
	"xs\\:p-4": "qpd",
	"xs\\:p-6": "rpd",
	"xs\\:pb-0": "djd",
	"xs\\:pb-6": "ejd",
	"xs\\:pl-1\\/10": "n2c",
	"xs\\:pl-6": "fjd",
	"xs\\:pr-1\\/6": "k6c",
	"xs\\:pt-4": "gjd",
	"xs\\:px-4": "yid",
	"xs\\:px-6": "zid",
	"xs\\:px-8": "ajd",
	"xs\\:py-3": "bjd",
	"xs\\:py-3\\.5": "j6c",
	"xs\\:py-6": "cjd",
	"xs\\:right-8": "g6c",
	"xs\\:rounded-large": "vmc",
	"xs\\:text-2xl": "o2c",
	"xs\\:text-4xl": "p2c",
	"xs\\:text-base": "vyc",
	"xs\\:text-sm": "l6c",
	"xs\\:text-xs": "m6c",
	"xs\\:w-1\\/4": "o-c",
	"xs\\:w-32": "xid",
	"z-0": "d0d",
	"z-10": "xud",
	"z-20": "yud",
	"z-30": "zud",
	"z-40": "avd",
	"z-50": "bvd"
}